mwps-0.0.0.dist-info/METADATA
mwps-0.0.0.dist-info/WHEEL
mwps-0.0.0.dist-info/license_files/LICENSE
mwps/__init__.py
mwps/mwps.abi3.so
mwps-0.0.0.dist-info/RECORD
