Metadata-Version: 2.1
Name: mwps
Version: 0.0.0
Classifier: Programming Language :: Rust
Classifier: Programming Language :: Python
Classifier: Programming Language :: Python :: 3
Classifier: Programming Language :: Python :: 3 :: Only
Classifier: Programming Language :: Python :: 3.7
Classifier: Programming Language :: Python :: 3.8
Classifier: Programming Language :: Python :: 3.9
Classifier: Programming Language :: Python :: Implementation :: CPython
Classifier: Programming Language :: Python :: Implementation :: PyPy
Classifier: Intended Audience :: Developers
Classifier: Intended Audience :: Information Technology
Classifier: Intended Audience :: System Administrators
Classifier: License :: OSI Approved :: MIT License
Classifier: Operating System :: Unix
Classifier: Operating System :: POSIX :: Linux
Classifier: Environment :: Console
Classifier: Environment :: MacOS X
Classifier: Topic :: Software Development :: Libraries :: Python Modules
Classifier: Topic :: Internet
License-File: LICENSE
Summary: Hypergraph Minimum-Weight Parity Subgraph (MWPS) Solver for Quantum LDPC Codes
Keywords: QEC,quantum-computing,error-correction,visualization
Home-Page: https://hyper-mwps.com
Author: Yue Wu <wuyue16pku@gmail.com>
Author-email: Yue Wu <wuyue16pku@gmail.com>
License: MIT
Requires-Python: >=3.7
Project-URL: Source Code, https://github.com/yuewuo/mwps
